{
  "object" : {
    "artifacts" : [

    ],
    "dependencies" : [
      {
        "basedOn" : null,
        "packageRef" : {
          "identity" : "swift-cmark",
          "kind" : "remoteSourceControl",
          "location" : "https://github.com/swiftlang/swift-cmark.git",
          "name" : "cmark-gfm"
        },
        "state" : {
          "checkoutState" : {
            "branch" : "gfm",
            "revision" : "924936d0427cb25a61169739a7660230bffa6ea6"
          },
          "name" : "sourceControlCheckout"
        },
        "subpath" : "swift-cmark"
      },
      {
        "basedOn" : null,
        "packageRef" : {
          "identity" : "swift-markdown",
          "kind" : "remoteSourceControl",
          "location" : "https://github.com/apple/swift-markdown.git",
          "name" : "swift-markdown"
        },
        "state" : {
          "checkoutState" : {
            "branch" : "main",
            "revision" : "ba1fbd1b242972b9aa79a3d1f213b5eed2e84921"
          },
          "name" : "sourceControlCheckout"
        },
        "subpath" : "swift-markdown"
      },
      {
        "basedOn" : null,
        "packageRef" : {
          "identity" : "yams",
          "kind" : "remoteSourceControl",
          "location" : "https://github.com/jpsim/Yams.git",
          "name" : "Yams"
        },
        "state" : {
          "checkoutState" : {
            "revision" : "3d6871d5b4a5cd519adf233fbb576e0a2af71c17",
            "version" : "5.4.0"
          },
          "name" : "sourceControlCheckout"
        },
        "subpath" : "Yams"
      }
    ],
    "prebuilts" : [

    ]
  },
  "version" : 7
}